LICENSE
MANIFEST.in
README.md
requirements.txt
setup.py
joker/flasky/__init__.py
joker/flasky/app.py
joker/flasky/auth.py
joker/flasky/context.py
joker/flasky/develop.py
joker/flasky/environ.py
joker/flasky/loggers.py
joker/flasky/pages.py
joker/flasky/security.py
joker/flasky/serialize.py
joker/flasky/viewutils.py
joker/flasky/templates/help.html
joker/flasky/templates/helplist.html
joker/flasky/templates/login.html
joker/flasky/templates/upload.html
joker/flasky/tools/__init__.py
joker/flasky/tools/docs.py
joker/flasky/tools/validation.py
joker/flasky/views/__init__.py
joker/flasky/views/admin_views.py
joker/flasky/views/ctxmap_views.py
joker_flasky.egg-info/PKG-INFO
joker_flasky.egg-info/SOURCES.txt
joker_flasky.egg-info/dependency_links.txt
joker_flasky.egg-info/namespace_packages.txt
joker_flasky.egg-info/not-zip-safe
joker_flasky.egg-info/requires.txt
joker_flasky.egg-info/top_level.txt